freq_statespace/__init__.py
freq_statespace/_best_linear_approximation.py
freq_statespace/_config.py
freq_statespace/_data_manager.py
freq_statespace/_frequency_response.py
freq_statespace/_misc.py
freq_statespace/_model_structures.py
freq_statespace/_nonlin_lfr.py
freq_statespace/_solve.py
freq_statespace/dep/__init__.py
freq_statespace/dep/fsid.py
freq_statespace/f_static/__init__.py
freq_statespace/f_static/_feature_maps.py
freq_statespace/f_static/_nonlin_funcs.py
freq_statespace-0.1.0.dist-info/METADATA
freq_statespace-0.1.0.dist-info/WHEEL
freq_statespace-0.1.0.dist-info/licenses/LICENSE
freq_statespace-0.1.0.dist-info/RECORD
