Metadata-Version: 2.4
Name: freq-statespace
Version: 0.1.0
Summary: Frequency-domain (nonlinear) state-space identification using JAX.
Project-URL: homepage, https://github.com/merijnfloren/freq-statespace
Author-email: Merijn Floren <merijn.floren@gmail.com>
License-Expression: MIT
License-File: LICENSE
Keywords: best-linear-approximation,equinox,frequency-domain,jax,nonlinear-benchmarks,nonlinear-regression,optimistix,optimization,state-space-models,subspace-identification,system-identification
Classifier: Development Status :: 3 - Alpha
Classifier: Intended Audience :: Developers
Classifier: Intended Audience :: Education
Classifier: Intended Audience :: Science/Research
Classifier: License :: OSI Approved :: MIT License
Classifier: Natural Language :: English
Classifier: Operating System :: OS Independent
Classifier: Programming Language :: Python :: 3
Requires-Python: >=3.10
Requires-Dist: equinox>=0.12.2
Requires-Dist: jax>=0.4.38
Requires-Dist: jaxtyping>=0.2.24
Requires-Dist: nonlinear-benchmarks
Requires-Dist: optax>=0.2.5
Requires-Dist: optimistix>=0.0.10
